instaresizer/__init__.py
instaresizer/instasize.py
instaresizer-0.0.6.dist-info/LICENSE
instaresizer-0.0.6.dist-info/METADATA
instaresizer-0.0.6.dist-info/WHEEL
instaresizer-0.0.6.dist-info/top_level.txt
instaresizer-0.0.6.dist-info/RECORD
