Metadata-Version: 2.1
Name: instaresizer
Version: 0.0.6
Summary: Returns a PIL Image object of instagram compatible aspect ratio when supplied with an image URL or an image object.
Home-page: https://github.com/roshanpty/instaresizer
Author: Roshan Thomas
Author-email: roshan@secvibe.com
License: UNKNOWN
Project-URL: Bug Tracker, https://github.com/roshanpty/instaresizer
Platform: UNKNOWN
Classifier: Programming Language :: Python :: 3
Classifier: License :: OSI Approved :: GNU General Public License v3 (GPLv3)
Classifier: Operating System :: OS Independent
Requires-Python: >=3.6
License-File: LICENSE
Requires-Dist: Pillow
Requires-Dist: requests
Requires-Dist: python-resize-image
